setup.py
soha/__init__.py
soha.egg-info/PKG-INFO
soha.egg-info/SOURCES.txt
soha.egg-info/dependency_links.txt
soha.egg-info/not-zip-safe
soha.egg-info/top_level.txt