Metadata-Version: 2.1
Name: soha
Version: 0.1
Summary: operation & greeting library
Author-email: piyushbedi2020@gmail.com
